gnmi_pb/__init__.py
gnmi_pb/gnmi_ext_pb2.py
gnmi_pb/gnmi_ext_pb2.pyi
gnmi_pb/gnmi_ext_pb2_grpc.py
gnmi_pb/gnmi_pb2.py
gnmi_pb/gnmi_pb2.pyi
gnmi_pb/gnmi_pb2_grpc.py
gnmi_pb-0.11.0.1.dist-info/LICENSE
gnmi_pb-0.11.0.1.dist-info/METADATA
gnmi_pb-0.11.0.1.dist-info/WHEEL
gnmi_pb-0.11.0.1.dist-info/top_level.txt
gnmi_pb-0.11.0.1.dist-info/RECORD
