Metadata-Version: 2.1
Name: gnmi-pb
Version: 0.11.0.1
Summary: Unofficial GNMI proto python distribution project
Maintainer-email: iPronics SW Team <support@ipronics.com>
License:                                  Apache License
Project-URL: Homepage, https://github.com/iPronics/gnmi-pb
Project-URL: Source, https://github.com/iPronics/gnmi-pb
Project-URL: Issues, https://github.com/iPronics/gnmi-pb/issues
Keywords: gNMI,proto
Classifier: Development Status :: 3 - Alpha
Classifier: License :: OSI Approved :: Apache Software License
Classifier: Operating System :: Microsoft :: Windows
Classifier: Operating System :: POSIX
Classifier: Operating System :: POSIX :: Linux
Classifier: Operating System :: Unix
Classifier: Operating System :: OS Independent
Classifier: Programming Language :: Python :: 3
Classifier: Topic :: Software Development :: Libraries
Classifier: Topic :: Communications
Classifier: Topic :: Scientific/Engineering
Requires-Python: >=3.11
License-File: LICENSE
Requires-Dist: grpcio>=1.68.1
Requires-Dist: grpcio-tools>=1.68.1
